CHANGES.rst
MANIFEST.in
README.md
README.rst
setup.py
dbskit/__init__.py
dbskit/util.py
dbskit.egg-info/PKG-INFO
dbskit.egg-info/SOURCES.txt
dbskit.egg-info/dependency_links.txt
dbskit.egg-info/requires.txt
dbskit.egg-info/top_level.txt
dbskit/mongo/__init__.py
dbskit/mongo/error.py
dbskit/mongo/handler.py
dbskit/mongo/orm.py
dbskit/mongo/suit.py
dbskit/mysql/__init__.py
dbskit/mysql/error.py
dbskit/mysql/handler.py
dbskit/mysql/orm.py
dbskit/mysql/suit.py
dbskit/test/__init__.py
dbskit/test/run.py