Metadata-Version: 1.0
Name: dbskit
Version: 1.1.0
Summary: wecatch dbskit
Home-page: https://github.com/listen-lavender/dbskit
Author: haokuan
Author-email: jingdaohao@gmail.com
License: UNKNOWN
Keywords: wecatch >
Platform: UNKNOWN
